{".class":"MypyFile","_fullname":"fluxflow.config","future_import_flags":[],"is_partial_stub_package":false,"is_stub":false,"names":{".class":"SymbolTable","BaseModel":{".class":"SymbolTableNode","cross_ref":"pydantic.main.BaseModel","kind":"Gdef"},"DataConfig":{".class":"SymbolTableNode","kind":"Gdef","node":{".class":"TypeInfo","_promote":[],"abstract_attributes":[],"alt_promote":null,"bases":["pydantic.main.BaseModel"],"dataclass_transform_spec":null,"declared_metaclass":null,"defn":{".class":"ClassDef","fullname":"fluxflow.config.DataConfig","name":"DataConfig","type_vars":[]},"deletable_attributes":[],"deprecated":null,"flags":[],"fullname":"fluxflow.config.DataConfig","has_param_spec_type":false,"metaclass_type":"pydantic._internal._model_construction.ModelMetaclass","metadata":{"dataclass":{"attributes":[{"alias":null,"column":4,"has_default":false,"is_in_init":false,"is_init_var":false,"is_neither_frozen_nor_nonfrozen":true,"kw_only":true,"line":214,"name":"__pydantic_extra__","type":{".class":"UnionType","items":[{".class":"Instance","args":["builtins.str",{".class":"AnyType","missing_import_name":null,"source_any":null,"type_of_any":2}],"extra_attrs":null,"type_ref":"builtins.dict"},{".class":"NoneType"}],"uses_pep604_syntax":true}},{"alias":null,"column":4,"has_default":false,"is_in_init":false,"is_init_var":false,"is_neither_frozen_nor_nonfrozen":true,"kw_only":true,"line":217,"name":"__pydantic_fields_set__","type":{".class":"Instance","args":["builtins.str"],"extra_attrs":null,"type_ref":"builtins.set"}},{"alias":null,"column":4,"has_default":false,"is_in_init":false,"is_init_var":false,"is_neither_frozen_nor_nonfrozen":true,"kw_only":true,"line":220,"name":"__pydantic_private__","type":{".class":"UnionType","items":[{".class":"Instance","args":["builtins.str",{".class":"AnyType","missing_import_name":null,"source_any":null,"type_of_any":2}],"extra_attrs":null,"type_ref":"builtins.dict"},{".class":"NoneType"}],"uses_pep604_syntax":true}},{"alias":null,"column":4,"has_default":true,"is_in_init":true,"is_init_var":false,"is_neither_frozen_nor_nonfrozen":false,"kw_only":true,"line":38,"name":"data_path","type":{".class":"UnionType","items":["builtins.str",{".class":"NoneType"}],"uses_pep604_syntax":false}},{"alias":null,"column":4,"has_default":true,"is_in_init":true,"is_init_var":false,"is_neither_frozen_nor_nonfrozen":false,"kw_only":true,"line":39,"name":"captions_file","type":{".class":"UnionType","items":["builtins.str",{".class":"NoneType"}],"uses_pep604_syntax":false}},{"alias":null,"column":4,"has_default":true,"is_in_init":true,"is_init_var":false,"is_neither_frozen_nor_nonfrozen":false,"kw_only":true,"line":42,"name":"use_tt2m","type":"builtins.bool"},{"alias":null,"column":4,"has_default":true,"is_in_init":true,"is_init_var":false,"is_neither_frozen_nor_nonfrozen":false,"kw_only":true,"line":45,"name":"tt2m_token","type":{".class":"UnionType","items":["builtins.str",{".class":"NoneType"}],"uses_pep604_syntax":false}},{"alias":null,"column":4,"has_default":true,"is_in_init":true,"is_init_var":false,"is_neither_frozen_nor_nonfrozen":false,"kw_only":true,"line":48,"name":"img_size","type":"builtins.int"},{"alias":null,"column":4,"has_default":true,"is_in_init":true,"is_init_var":false,"is_neither_frozen_nor_nonfrozen":false,"kw_only":true,"line":49,"name":"channels","type":"builtins.int"},{"alias":null,"column":4,"has_default":true,"is_in_init":true,"is_init_var":false,"is_neither_frozen_nor_nonfrozen":false,"kw_only":true,"line":52,"name":"tokenizer_name","type":"builtins.str"}],"frozen":false},"dataclass_tag":{}},"module_name":"fluxflow.config","mro":["fluxflow.config.DataConfig","pydantic.main.BaseModel","builtins.object"],"names":{".class":"SymbolTable","__dataclass_fields__":{".class":"SymbolTableNode","kind":"Mdef","node":{".class":"Var","flags":["is_classvar","is_ready"],"fullname":"fluxflow.config.DataConfig.__dataclass_fields__","name":"__dataclass_fields__","setter_type":null,"type":{".class":"Instance","args":["builtins.str",{".class":"AnyType","missing_import_name":null,"source_any":null,"type_of_any":2}],"extra_attrs":null,"type_ref":"builtins.dict"}},"plugin_generated":true},"__init__":{".class":"SymbolTableNode","kind":"Mdef","node":{".class":"FuncDef","abstract_status":0,"arg_kinds":[0,5,5,5,5,5,5,5],"arg_names":["self","data_path","captions_file","use_tt2m","tt2m_token","img_size","channels","tokenizer_name"],"dataclass_transform_spec":null,"deprecated":null,"flags":[],"fullname":"fluxflow.config.DataConfig.__init__","name":"__init__","original_first_arg":"self","type":{".class":"CallableType","arg_kinds":[0,5,5,5,5,5,5,5],"arg_names":["self","data_path","captions_file","use_tt2m","tt2m_token","img_size","channels","tokenizer_name"],"arg_types":["fluxflow.config.DataConfig",{".class":"UnionType","items":["builtins.str",{".class":"NoneType"}],"uses_pep604_syntax":false},{".class":"UnionType","items":["builtins.str",{".class":"NoneType"}],"uses_pep604_syntax":false},"builtins.bool",{".class":"UnionType","items":["builtins.str",{".class":"NoneType"}],"uses_pep604_syntax":false},"builtins.int","builtins.int","builtins.str"],"fallback":"builtins.function","from_concatenate":false,"implicit":false,"imprecise_arg_kinds":false,"is_bound":false,"is_ellipsis_args":false,"name":"__init__ of DataConfig","ret_type":{".class":"NoneType"},"type_guard":null,"type_is":null,"unpack_kwargs":false,"variables":[]}},"plugin_generated":true},"__match_args__":{".class":"SymbolTableNode","kind":"Mdef","node":{".class":"Var","flags":["is_ready","allow_incompatible_override"],"fullname":"fluxflow.config.DataConfig.__match_args__","name":"__match_args__","setter_type":null,"type":{".class":"TupleType","implicit":false,"items":[],"partial_fallback":{".class":"Instance","args":[{".class":"AnyType","missing_import_name":null,"source_any":null,"type_of_any":6}],"extra_attrs":null,"type_ref":"builtins.tuple"}}},"plugin_generated":true},"__mypy-replace":{".class":"SymbolTableNode","kind":"Mdef","node":{".class":"Decorator","func":{".class":"FuncDef","abstract_status":0,"arg_kinds":[5,5,5,5,5,5,5,5,5,5],"arg_names":["__pydantic_extra__","__pydantic_fields_set__","__pydantic_private__","data_path","captions_file","use_tt2m","tt2m_token","img_size","channels","tokenizer_name"],"dataclass_transform_spec":null,"deprecated":null,"flags":["is_static","is_decorated"],"fullname":"fluxflow.config.DataConfig.__mypy-replace","name":"__mypy-replace","original_first_arg":"__pydantic_extra__","type":{".class":"CallableType","arg_kinds":[5,5,5,5,5,5,5,5,5,5],"arg_names":["__pydantic_extra__","__pydantic_fields_set__","__pydantic_private__","data_path","captions_file","use_tt2m","tt2m_token","img_size","channels","tokenizer_name"],"arg_types":[{".class":"UnionType","items":[{".class":"Instance","args":["builtins.str",{".class":"AnyType","missing_import_name":null,"source_any":null,"type_of_any":2}],"extra_attrs":null,"type_ref":"builtins.dict"},{".class":"NoneType"}],"uses_pep604_syntax":false},{".class":"Instance","args":["builtins.str"],"extra_attrs":null,"type_ref":"builtins.set"},{".class":"UnionType","items":[{".class":"Instance","args":["builtins.str",{".class":"AnyType","missing_import_name":null,"source_any":null,"type_of_any":2}],"extra_attrs":null,"type_ref":"builtins.dict"},{".class":"NoneType"}],"uses_pep604_syntax":false},{".class":"UnionType","items":["builtins.str",{".class":"NoneType"}],"uses_pep604_syntax":false},{".class":"UnionType","items":["builtins.str",{".class":"NoneType"}],"uses_pep604_syntax":false},"builtins.bool",{".class":"UnionType","items":["builtins.str",{".class":"NoneType"}],"uses_pep604_syntax":false},"builtins.int","builtins.int","builtins.str"],"fallback":"builtins.function","from_concatenate":false,"implicit":false,"imprecise_arg_kinds":false,"is_bound":false,"is_ellipsis_args":false,"name":"__mypy-replace of DataConfig","ret_type":{".class":"NoneType"},"type_guard":null,"type_is":null,"unpack_kwargs":false,"variables":[]}},"is_overload":false,"var":{".class":"Var","flags":["is_staticmethod","is_ready"],"fullname":"fluxflow.config.DataConfig.__mypy-replace","name":"__mypy-replace","setter_type":null,"type":{".class":"CallableType","arg_kinds":[5,5,5,5,5,5,5,5,5,5],"arg_names":["__pydantic_extra__","__pydantic_fields_set__","__pydantic_private__","data_path","captions_file","use_tt2m","tt2m_token","img_size","channels","tokenizer_name"],"arg_types":[{".class":"UnionType","items":[{".class":"Instance","args":["builtins.str",{".class":"AnyType","missing_import_name":null,"source_any":null,"type_of_any":2}],"extra_attrs":null,"type_ref":"builtins.dict"},{".class":"NoneType"}],"uses_pep604_syntax":false},{".class":"Instance","args":["builtins.str"],"extra_attrs":null,"type_ref":"builtins.set"},{".class":"UnionType","items":[{".class":"Instance","args":["builtins.str",{".class":"AnyType","missing_import_name":null,"source_any":null,"type_of_any":2}],"extra_attrs":null,"type_ref":"builtins.dict"},{".class":"NoneType"}],"uses_pep604_syntax":false},{".class":"UnionType","items":["builtins.str",{".class":"NoneType"}],"uses_pep604_syntax":false},{".class":"UnionType","items":["builtins.str",{".class":"NoneType"}],"uses_pep604_syntax":false},"builtins.bool",{".class":"UnionType","items":["builtins.str",{".class":"NoneType"}],"uses_pep604_syntax":false},"builtins.int","builtins.int","builtins.str"],"fallback":"builtins.function","from_concatenate":false,"implicit":false,"imprecise_arg_kinds":false,"is_bound":false,"is_ellipsis_args":false,"name":"__mypy-replace of DataConfig","ret_type":{".class":"NoneType"},"type_guard":null,"type_is":null,"unpack_kwargs":false,"variables":[]}}},"plugin_generated":true},"captions_file":{".class":"SymbolTableNode","kind":"Mdef","node":{".class":"Var","flags":["is_initialized_in_class","is_ready","has_explicit_value"],"fullname":"fluxflow.config.DataConfig.captions_file","name":"captions_file","setter_type":null,"type":{".class":"UnionType","items":["builtins.str",{".class":"NoneType"}],"uses_pep604_syntax":false}}},"channels":{".class":"SymbolTableNode","kind":"Mdef","node":{".class":"Var","flags":["is_initialized_in_class","is_ready","has_explicit_value"],"fullname":"fluxflow.config.DataConfig.channels","name":"channels","setter_type":null,"type":"builtins.int"}},"data_path":{".class":"SymbolTableNode","kind":"Mdef","node":{".class":"Var","flags":["is_initialized_in_class","is_ready","has_explicit_value"],"fullname":"fluxflow.config.DataConfig.data_path","name":"data_path","setter_type":null,"type":{".class":"UnionType","items":["builtins.str",{".class":"NoneType"}],"uses_pep604_syntax":false}}},"img_size":{".class":"SymbolTableNode","kind":"Mdef","node":{".class":"Var","flags":["is_initialized_in_class","is_ready","has_explicit_value"],"fullname":"fluxflow.config.DataConfig.img_size","name":"img_size","setter_type":null,"type":"builtins.int"}},"tokenizer_name":{".class":"SymbolTableNode","kind":"Mdef","node":{".class":"Var","flags":["is_initialized_in_class","is_ready","has_explicit_value"],"fullname":"fluxflow.config.DataConfig.tokenizer_name","name":"tokenizer_name","setter_type":null,"type":"builtins.str"}},"tt2m_token":{".class":"SymbolTableNode","kind":"Mdef","node":{".class":"Var","flags":["is_initialized_in_class","is_ready","has_explicit_value"],"fullname":"fluxflow.config.DataConfig.tt2m_token","name":"tt2m_token","setter_type":null,"type":{".class":"UnionType","items":["builtins.str",{".class":"NoneType"}],"uses_pep604_syntax":false}}},"use_tt2m":{".class":"SymbolTableNode","kind":"Mdef","node":{".class":"Var","flags":["is_initialized_in_class","is_ready","has_explicit_value"],"fullname":"fluxflow.config.DataConfig.use_tt2m","name":"use_tt2m","setter_type":null,"type":"builtins.bool"}},"validate_paths":{".class":"SymbolTableNode","kind":"Mdef","node":{".class":"Decorator","func":{".class":"FuncDef","abstract_status":0,"arg_kinds":[0,0],"arg_names":["cls","v"],"dataclass_transform_spec":null,"deprecated":null,"flags":["is_class","is_decorated"],"fullname":"fluxflow.config.DataConfig.validate_paths","name":"validate_paths","original_first_arg":"cls","type":null},"is_overload":false,"var":{".class":"Var","flags":["is_initialized_in_class","is_classmethod","is_ready","is_inferred"],"fullname":"fluxflow.config.DataConfig.validate_paths","name":"validate_paths","setter_type":null,"type":{".class":"CallableType","arg_kinds":[0,0],"arg_names":["cls","v"],"arg_types":[{".class":"TypeType","is_type_form":false,"item":"fluxflow.config.DataConfig"},{".class":"AnyType","missing_import_name":null,"source_any":null,"type_of_any":1}],"fallback":"builtins.function","from_concatenate":false,"implicit":true,"imprecise_arg_kinds":false,"is_bound":false,"is_ellipsis_args":false,"name":"validate_paths of DataConfig","ret_type":{".class":"AnyType","missing_import_name":null,"source_any":null,"type_of_any":1},"type_guard":null,"type_is":null,"unpack_kwargs":false,"variables":[]}}}}},"self_type":{".class":"TypeVarType","default":{".class":"AnyType","missing_import_name":null,"source_any":null,"type_of_any":4},"fullname":"fluxflow.config.DataConfig.Self","id":0,"name":"Self","namespace":"","upper_bound":"fluxflow.config.DataConfig","values":[],"variance":0},"slots":null,"tuple_type":null,"type_vars":[],"typeddict_type":null}},"Field":{".class":"SymbolTableNode","cross_ref":"pydantic.fields.Field","kind":"Gdef"},"FluxFlowConfig":{".class":"SymbolTableNode","kind":"Gdef","node":{".class":"TypeInfo","_promote":[],"abstract_attributes":[],"alt_promote":null,"bases":["pydantic.main.BaseModel"],"dataclass_transform_spec":null,"declared_metaclass":null,"defn":{".class":"ClassDef","fullname":"fluxflow.config.FluxFlowConfig","name":"FluxFlowConfig","type_vars":[]},"deletable_attributes":[],"deprecated":null,"flags":[],"fullname":"fluxflow.config.FluxFlowConfig","has_param_spec_type":false,"metaclass_type":"pydantic._internal._model_construction.ModelMetaclass","metadata":{"dataclass":{"attributes":[{"alias":null,"column":4,"has_default":false,"is_in_init":false,"is_init_var":false,"is_neither_frozen_nor_nonfrozen":true,"kw_only":true,"line":214,"name":"__pydantic_extra__","type":{".class":"UnionType","items":[{".class":"Instance","args":["builtins.str",{".class":"AnyType","missing_import_name":null,"source_any":null,"type_of_any":2}],"extra_attrs":null,"type_ref":"builtins.dict"},{".class":"NoneType"}],"uses_pep604_syntax":true}},{"alias":null,"column":4,"has_default":false,"is_in_init":false,"is_init_var":false,"is_neither_frozen_nor_nonfrozen":true,"kw_only":true,"line":217,"name":"__pydantic_fields_set__","type":{".class":"Instance","args":["builtins.str"],"extra_attrs":null,"type_ref":"builtins.set"}},{"alias":null,"column":4,"has_default":false,"is_in_init":false,"is_init_var":false,"is_neither_frozen_nor_nonfrozen":true,"kw_only":true,"line":220,"name":"__pydantic_private__","type":{".class":"UnionType","items":[{".class":"Instance","args":["builtins.str",{".class":"AnyType","missing_import_name":null,"source_any":null,"type_of_any":2}],"extra_attrs":null,"type_ref":"builtins.dict"},{".class":"NoneType"}],"uses_pep604_syntax":true}},{"alias":null,"column":4,"has_default":true,"is_in_init":true,"is_init_var":false,"is_neither_frozen_nor_nonfrozen":false,"kw_only":true,"line":128,"name":"model","type":"fluxflow.config.ModelConfig"},{"alias":null,"column":4,"has_default":true,"is_in_init":true,"is_init_var":false,"is_neither_frozen_nor_nonfrozen":false,"kw_only":true,"line":129,"name":"data","type":"fluxflow.config.DataConfig"},{"alias":null,"column":4,"has_default":true,"is_in_init":true,"is_init_var":false,"is_neither_frozen_nor_nonfrozen":false,"kw_only":true,"line":130,"name":"training","type":"fluxflow.config.TrainingConfig"},{"alias":null,"column":4,"has_default":true,"is_in_init":true,"is_init_var":false,"is_neither_frozen_nor_nonfrozen":false,"kw_only":true,"line":131,"name":"optimization","type":"fluxflow.config.OptimizationConfig"},{"alias":null,"column":4,"has_default":true,"is_in_init":true,"is_init_var":false,"is_neither_frozen_nor_nonfrozen":false,"kw_only":true,"line":132,"name":"output","type":"fluxflow.config.OutputConfig"},{"alias":null,"column":4,"has_default":true,"is_in_init":true,"is_init_var":false,"is_neither_frozen_nor_nonfrozen":false,"kw_only":true,"line":133,"name":"model_checkpoint","type":{".class":"UnionType","items":["builtins.str",{".class":"NoneType"}],"uses_pep604_syntax":false}}],"frozen":false},"dataclass_tag":{}},"module_name":"fluxflow.config","mro":["fluxflow.config.FluxFlowConfig","pydantic.main.BaseModel","builtins.object"],"names":{".class":"SymbolTable","__dataclass_fields__":{".class":"SymbolTableNode","kind":"Mdef","node":{".class":"Var","flags":["is_classvar","is_ready"],"fullname":"fluxflow.config.FluxFlowConfig.__dataclass_fields__","name":"__dataclass_fields__","setter_type":null,"type":{".class":"Instance","args":["builtins.str",{".class":"AnyType","missing_import_name":null,"source_any":null,"type_of_any":2}],"extra_attrs":null,"type_ref":"builtins.dict"}},"plugin_generated":true},"__init__":{".class":"SymbolTableNode","kind":"Mdef","node":{".class":"FuncDef","abstract_status":0,"arg_kinds":[0,5,5,5,5,5,5],"arg_names":["self","model","data","training","optimization","output","model_checkpoint"],"dataclass_transform_spec":null,"deprecated":null,"flags":[],"fullname":"fluxflow.config.FluxFlowConfig.__init__","name":"__init__","original_first_arg":"self","type":{".class":"CallableType","arg_kinds":[0,5,5,5,5,5,5],"arg_names":["self","model","data","training","optimization","output","model_checkpoint"],"arg_types":["fluxflow.config.FluxFlowConfig","fluxflow.config.ModelConfig","fluxflow.config.DataConfig","fluxflow.config.TrainingConfig","fluxflow.config.OptimizationConfig","fluxflow.config.OutputConfig",{".class":"UnionType","items":["builtins.str",{".class":"NoneType"}],"uses_pep604_syntax":false}],"fallback":"builtins.function","from_concatenate":false,"implicit":false,"imprecise_arg_kinds":false,"is_bound":false,"is_ellipsis_args":false,"name":"__init__ of FluxFlowConfig","ret_type":{".class":"NoneType"},"type_guard":null,"type_is":null,"unpack_kwargs":false,"variables":[]}},"plugin_generated":true},"__match_args__":{".class":"SymbolTableNode","kind":"Mdef","node":{".class":"Var","flags":["is_ready","allow_incompatible_override"],"fullname":"fluxflow.config.FluxFlowConfig.__match_args__","name":"__match_args__","setter_type":null,"type":{".class":"TupleType","implicit":false,"items":[],"partial_fallback":{".class":"Instance","args":[{".class":"AnyType","missing_import_name":null,"source_any":null,"type_of_any":6}],"extra_attrs":null,"type_ref":"builtins.tuple"}}},"plugin_generated":true},"__mypy-replace":{".class":"SymbolTableNode","kind":"Mdef","node":{".class":"Decorator","func":{".class":"FuncDef","abstract_status":0,"arg_kinds":[5,5,5,5,5,5,5,5,5],"arg_names":["__pydantic_extra__","__pydantic_fields_set__","__pydantic_private__","model","data","training","optimization","output","model_checkpoint"],"dataclass_transform_spec":null,"deprecated":null,"flags":["is_static","is_decorated"],"fullname":"fluxflow.config.FluxFlowConfig.__mypy-replace","name":"__mypy-replace","original_first_arg":"__pydantic_extra__","type":{".class":"CallableType","arg_kinds":[5,5,5,5,5,5,5,5,5],"arg_names":["__pydantic_extra__","__pydantic_fields_set__","__pydantic_private__","model","data","training","optimization","output","model_checkpoint"],"arg_types":[{".class":"UnionType","items":[{".class":"Instance","args":["builtins.str",{".class":"AnyType","missing_import_name":null,"source_any":null,"type_of_any":2}],"extra_attrs":null,"type_ref":"builtins.dict"},{".class":"NoneType"}],"uses_pep604_syntax":false},{".class":"Instance","args":["builtins.str"],"extra_attrs":null,"type_ref":"builtins.set"},{".class":"UnionType","items":[{".class":"Instance","args":["builtins.str",{".class":"AnyType","missing_import_name":null,"source_any":null,"type_of_any":2}],"extra_attrs":null,"type_ref":"builtins.dict"},{".class":"NoneType"}],"uses_pep604_syntax":false},"fluxflow.config.ModelConfig","fluxflow.config.DataConfig","fluxflow.config.TrainingConfig","fluxflow.config.OptimizationConfig","fluxflow.config.OutputConfig",{".class":"UnionType","items":["builtins.str",{".class":"NoneType"}],"uses_pep604_syntax":false}],"fallback":"builtins.function","from_concatenate":false,"implicit":false,"imprecise_arg_kinds":false,"is_bound":false,"is_ellipsis_args":false,"name":"__mypy-replace of FluxFlowConfig","ret_type":{".class":"NoneType"},"type_guard":null,"type_is":null,"unpack_kwargs":false,"variables":[]}},"is_overload":false,"var":{".class":"Var","flags":["is_staticmethod","is_ready"],"fullname":"fluxflow.config.FluxFlowConfig.__mypy-replace","name":"__mypy-replace","setter_type":null,"type":{".class":"CallableType","arg_kinds":[5,5,5,5,5,5,5,5,5],"arg_names":["__pydantic_extra__","__pydantic_fields_set__","__pydantic_private__","model","data","training","optimization","output","model_checkpoint"],"arg_types":[{".class":"UnionType","items":[{".class":"Instance","args":["builtins.str",{".class":"AnyType","missing_import_name":null,"source_any":null,"type_of_any":2}],"extra_attrs":null,"type_ref":"builtins.dict"},{".class":"NoneType"}],"uses_pep604_syntax":false},{".class":"Instance","args":["builtins.str"],"extra_attrs":null,"type_ref":"builtins.set"},{".class":"UnionType","items":[{".class":"Instance","args":["builtins.str",{".class":"AnyType","missing_import_name":null,"source_any":null,"type_of_any":2}],"extra_attrs":null,"type_ref":"builtins.dict"},{".class":"NoneType"}],"uses_pep604_syntax":false},"fluxflow.config.ModelConfig","fluxflow.config.DataConfig","fluxflow.config.TrainingConfig","fluxflow.config.OptimizationConfig","fluxflow.config.OutputConfig",{".class":"UnionType","items":["builtins.str",{".class":"NoneType"}],"uses_pep604_syntax":false}],"fallback":"builtins.function","from_concatenate":false,"implicit":false,"imprecise_arg_kinds":false,"is_bound":false,"is_ellipsis_args":false,"name":"__mypy-replace of FluxFlowConfig","ret_type":{".class":"NoneType"},"type_guard":null,"type_is":null,"unpack_kwargs":false,"variables":[]}}},"plugin_generated":true},"data":{".class":"SymbolTableNode","kind":"Mdef","node":{".class":"Var","flags":["is_initialized_in_class","is_ready","has_explicit_value"],"fullname":"fluxflow.config.FluxFlowConfig.data","name":"data","setter_type":null,"type":"fluxflow.config.DataConfig"}},"from_yaml":{".class":"SymbolTableNode","kind":"Mdef","node":{".class":"Decorator","func":{".class":"FuncDef","abstract_status":0,"arg_kinds":[0,0],"arg_names":["cls","path"],"dataclass_transform_spec":null,"deprecated":null,"flags":["is_class","is_decorated","is_trivial_self"],"fullname":"fluxflow.config.FluxFlowConfig.from_yaml","name":"from_yaml","original_first_arg":"cls","type":{".class":"CallableType","arg_kinds":[0,0],"arg_names":["cls","path"],"arg_types":[{".class":"TypeType","is_type_form":false,"item":"fluxflow.config.FluxFlowConfig"},{".class":"UnionType","items":["builtins.str","pathlib.Path"],"uses_pep604_syntax":true}],"fallback":"builtins.function","from_concatenate":false,"implicit":false,"imprecise_arg_kinds":false,"is_bound":false,"is_ellipsis_args":false,"name":"from_yaml of FluxFlowConfig","ret_type":"fluxflow.config.FluxFlowConfig","type_guard":null,"type_is":null,"unpack_kwargs":false,"variables":[]}},"is_overload":false,"var":{".class":"Var","flags":["is_initialized_in_class","is_classmethod","is_ready","is_inferred"],"fullname":"fluxflow.config.FluxFlowConfig.from_yaml","name":"from_yaml","setter_type":null,"type":{".class":"CallableType","arg_kinds":[0,0],"arg_names":["cls","path"],"arg_types":[{".class":"TypeType","is_type_form":false,"item":"fluxflow.config.FluxFlowConfig"},{".class":"UnionType","items":["builtins.str","pathlib.Path"],"uses_pep604_syntax":true}],"fallback":"builtins.function","from_concatenate":false,"implicit":false,"imprecise_arg_kinds":false,"is_bound":false,"is_ellipsis_args":false,"name":"from_yaml of FluxFlowConfig","ret_type":"fluxflow.config.FluxFlowConfig","type_guard":null,"type_is":null,"unpack_kwargs":false,"variables":[]}}}},"model":{".class":"SymbolTableNode","kind":"Mdef","node":{".class":"Var","flags":["is_initialized_in_class","is_ready","has_explicit_value"],"fullname":"fluxflow.config.FluxFlowConfig.model","name":"model","setter_type":null,"type":"fluxflow.config.ModelConfig"}},"model_checkpoint":{".class":"SymbolTableNode","kind":"Mdef","node":{".class":"Var","flags":["is_initialized_in_class","is_ready","has_explicit_value"],"fullname":"fluxflow.config.FluxFlowConfig.model_checkpoint","name":"model_checkpoint","setter_type":null,"type":{".class":"UnionType","items":["builtins.str",{".class":"NoneType"}],"uses_pep604_syntax":false}}},"optimization":{".class":"SymbolTableNode","kind":"Mdef","node":{".class":"Var","flags":["is_initialized_in_class","is_ready","has_explicit_value"],"fullname":"fluxflow.config.FluxFlowConfig.optimization","name":"optimization","setter_type":null,"type":"fluxflow.config.OptimizationConfig"}},"output":{".class":"SymbolTableNode","kind":"Mdef","node":{".class":"Var","flags":["is_initialized_in_class","is_ready","has_explicit_value"],"fullname":"fluxflow.config.FluxFlowConfig.output","name":"output","setter_type":null,"type":"fluxflow.config.OutputConfig"}},"to_yaml":{".class":"SymbolTableNode","kind":"Mdef","node":{".class":"FuncDef","abstract_status":0,"arg_kinds":[0,0],"arg_names":["self","path"],"dataclass_transform_spec":null,"deprecated":null,"flags":["is_trivial_self"],"fullname":"fluxflow.config.FluxFlowConfig.to_yaml","name":"to_yaml","original_first_arg":"self","type":{".class":"CallableType","arg_kinds":[0,0],"arg_names":["self","path"],"arg_types":["fluxflow.config.FluxFlowConfig",{".class":"UnionType","items":["builtins.str","pathlib.Path"],"uses_pep604_syntax":true}],"fallback":"builtins.function","from_concatenate":false,"implicit":false,"imprecise_arg_kinds":false,"is_bound":false,"is_ellipsis_args":false,"name":"to_yaml of FluxFlowConfig","ret_type":{".class":"NoneType"},"type_guard":null,"type_is":null,"unpack_kwargs":false,"variables":[]}}},"training":{".class":"SymbolTableNode","kind":"Mdef","node":{".class":"Var","flags":["is_initialized_in_class","is_ready","has_explicit_value"],"fullname":"fluxflow.config.FluxFlowConfig.training","name":"training","setter_type":null,"type":"fluxflow.config.TrainingConfig"}},"validate_all":{".class":"SymbolTableNode","kind":"Mdef","node":{".class":"FuncDef","abstract_status":0,"arg_kinds":[0],"arg_names":["self"],"dataclass_transform_spec":null,"deprecated":null,"flags":["is_trivial_self"],"fullname":"fluxflow.config.FluxFlowConfig.validate_all","name":"validate_all","original_first_arg":"self","type":{".class":"CallableType","arg_kinds":[0],"arg_names":["self"],"arg_types":["fluxflow.config.FluxFlowConfig"],"fallback":"builtins.function","from_concatenate":false,"implicit":false,"imprecise_arg_kinds":false,"is_bound":false,"is_ellipsis_args":false,"name":"validate_all of FluxFlowConfig","ret_type":{".class":"NoneType"},"type_guard":null,"type_is":null,"unpack_kwargs":false,"variables":[]}}},"validate_dataset":{".class":"SymbolTableNode","kind":"Mdef","node":{".class":"FuncDef","abstract_status":0,"arg_kinds":[0],"arg_names":["self"],"dataclass_transform_spec":null,"deprecated":null,"flags":["is_trivial_self"],"fullname":"fluxflow.config.FluxFlowConfig.validate_dataset","name":"validate_dataset","original_first_arg":"self","type":{".class":"CallableType","arg_kinds":[0],"arg_names":["self"],"arg_types":["fluxflow.config.FluxFlowConfig"],"fallback":"builtins.function","from_concatenate":false,"implicit":false,"imprecise_arg_kinds":false,"is_bound":false,"is_ellipsis_args":false,"name":"validate_dataset of FluxFlowConfig","ret_type":{".class":"NoneType"},"type_guard":null,"type_is":null,"unpack_kwargs":false,"variables":[]}}},"validate_training_mode":{".class":"SymbolTableNode","kind":"Mdef","node":{".class":"FuncDef","abstract_status":0,"arg_kinds":[0],"arg_names":["self"],"dataclass_transform_spec":null,"deprecated":null,"flags":["is_trivial_self"],"fullname":"fluxflow.config.FluxFlowConfig.validate_training_mode","name":"validate_training_mode","original_first_arg":"self","type":{".class":"CallableType","arg_kinds":[0],"arg_names":["self"],"arg_types":["fluxflow.config.FluxFlowConfig"],"fallback":"builtins.function","from_concatenate":false,"implicit":false,"imprecise_arg_kinds":false,"is_bound":false,"is_ellipsis_args":false,"name":"validate_training_mode of FluxFlowConfig","ret_type":{".class":"NoneType"},"type_guard":null,"type_is":null,"unpack_kwargs":false,"variables":[]}}}},"self_type":{".class":"TypeVarType","default":{".class":"AnyType","missing_import_name":null,"source_any":null,"type_of_any":4},"fullname":"fluxflow.config.FluxFlowConfig.Self","id":0,"name":"Self","namespace":"","upper_bound":"fluxflow.config.FluxFlowConfig","values":[],"variance":0},"slots":null,"tuple_type":null,"type_vars":[],"typeddict_type":null}},"List":{".class":"SymbolTableNode","cross_ref":"typing.List","kind":"Gdef"},"Literal":{".class":"SymbolTableNode","cross_ref":"typing.Literal","kind":"Gdef"},"ModelConfig":{".class":"SymbolTableNode","kind":"Gdef","node":{".class":"TypeInfo","_promote":[],"abstract_attributes":[],"alt_promote":null,"bases":["pydantic.main.BaseModel"],"dataclass_transform_spec":null,"declared_metaclass":null,"defn":{".class":"ClassDef","fullname":"fluxflow.config.ModelConfig","name":"ModelConfig","type_vars":[]},"deletable_attributes":[],"deprecated":null,"flags":[],"fullname":"fluxflow.config.ModelConfig","has_param_spec_type":false,"metaclass_type":"pydantic._internal._model_construction.ModelMetaclass","metadata":{"dataclass":{"attributes":[{"alias":null,"column":4,"has_default":false,"is_in_init":false,"is_init_var":false,"is_neither_frozen_nor_nonfrozen":true,"kw_only":true,"line":214,"name":"__pydantic_extra__","type":{".class":"UnionType","items":[{".class":"Instance","args":["builtins.str",{".class":"AnyType","missing_import_name":null,"source_any":null,"type_of_any":2}],"extra_attrs":null,"type_ref":"builtins.dict"},{".class":"NoneType"}],"uses_pep604_syntax":true}},{"alias":null,"column":4,"has_default":false,"is_in_init":false,"is_init_var":false,"is_neither_frozen_nor_nonfrozen":true,"kw_only":true,"line":217,"name":"__pydantic_fields_set__","type":{".class":"Instance","args":["builtins.str"],"extra_attrs":null,"type_ref":"builtins.set"}},{"alias":null,"column":4,"has_default":false,"is_in_init":false,"is_init_var":false,"is_neither_frozen_nor_nonfrozen":true,"kw_only":true,"line":220,"name":"__pydantic_private__","type":{".class":"UnionType","items":[{".class":"Instance","args":["builtins.str",{".class":"AnyType","missing_import_name":null,"source_any":null,"type_of_any":2}],"extra_attrs":null,"type_ref":"builtins.dict"},{".class":"NoneType"}],"uses_pep604_syntax":true}},{"alias":null,"column":4,"has_default":true,"is_in_init":true,"is_init_var":false,"is_neither_frozen_nor_nonfrozen":false,"kw_only":true,"line":17,"name":"vae_dim","type":"builtins.int"},{"alias":null,"column":4,"has_default":true,"is_in_init":true,"is_init_var":false,"is_neither_frozen_nor_nonfrozen":false,"kw_only":true,"line":23,"name":"feature_maps_dim","type":"builtins.int"},{"alias":null,"column":4,"has_default":true,"is_in_init":true,"is_init_var":false,"is_neither_frozen_nor_nonfrozen":false,"kw_only":true,"line":26,"name":"feature_maps_dim_disc","type":"builtins.int"},{"alias":null,"column":4,"has_default":true,"is_in_init":true,"is_init_var":false,"is_neither_frozen_nor_nonfrozen":false,"kw_only":true,"line":29,"name":"text_embedding_dim","type":"builtins.int"},{"alias":null,"column":4,"has_default":true,"is_in_init":true,"is_init_var":false,"is_neither_frozen_nor_nonfrozen":false,"kw_only":true,"line":30,"name":"pretrained_bert_model","type":{".class":"UnionType","items":["builtins.str",{".class":"NoneType"}],"uses_pep604_syntax":false}}],"frozen":false},"dataclass_tag":{}},"module_name":"fluxflow.config","mro":["fluxflow.config.ModelConfig","pydantic.main.BaseModel","builtins.object"],"names":{".class":"SymbolTable","__dataclass_fields__":{".class":"SymbolTableNode","kind":"Mdef","node":{".class":"Var","flags":["is_classvar","is_ready"],"fullname":"fluxflow.config.ModelConfig.__dataclass_fields__","name":"__dataclass_fields__","setter_type":null,"type":{".class":"Instance","args":["builtins.str",{".class":"AnyType","missing_import_name":null,"source_any":null,"type_of_any":2}],"extra_attrs":null,"type_ref":"builtins.dict"}},"plugin_generated":true},"__init__":{".class":"SymbolTableNode","kind":"Mdef","node":{".class":"FuncDef","abstract_status":0,"arg_kinds":[0,5,5,5,5,5],"arg_names":["self","vae_dim","feature_maps_dim","feature_maps_dim_disc","text_embedding_dim","pretrained_bert_model"],"dataclass_transform_spec":null,"deprecated":null,"flags":[],"fullname":"fluxflow.config.ModelConfig.__init__","name":"__init__","original_first_arg":"self","type":{".class":"CallableType","arg_kinds":[0,5,5,5,5,5],"arg_names":["self","vae_dim","feature_maps_dim","feature_maps_dim_disc","text_embedding_dim","pretrained_bert_model"],"arg_types":["fluxflow.config.ModelConfig","builtins.int","builtins.int","builtins.int","builtins.int",{".class":"UnionType","items":["builtins.str",{".class":"NoneType"}],"uses_pep604_syntax":false}],"fallback":"builtins.function","from_concatenate":false,"implicit":false,"imprecise_arg_kinds":false,"is_bound":false,"is_ellipsis_args":false,"name":"__init__ of ModelConfig","ret_type":{".class":"NoneType"},"type_guard":null,"type_is":null,"unpack_kwargs":false,"variables":[]}},"plugin_generated":true},"__match_args__":{".class":"SymbolTableNode","kind":"Mdef","node":{".class":"Var","flags":["is_ready","allow_incompatible_override"],"fullname":"fluxflow.config.ModelConfig.__match_args__","name":"__match_args__","setter_type":null,"type":{".class":"TupleType","implicit":false,"items":[],"partial_fallback":{".class":"Instance","args":[{".class":"AnyType","missing_import_name":null,"source_any":null,"type_of_any":6}],"extra_attrs":null,"type_ref":"builtins.tuple"}}},"plugin_generated":true},"__mypy-replace":{".class":"SymbolTableNode","kind":"Mdef","node":{".class":"Decorator","func":{".class":"FuncDef","abstract_status":0,"arg_kinds":[5,5,5,5,5,5,5,5],"arg_names":["__pydantic_extra__","__pydantic_fields_set__","__pydantic_private__","vae_dim","feature_maps_dim","feature_maps_dim_disc","text_embedding_dim","pretrained_bert_model"],"dataclass_transform_spec":null,"deprecated":null,"flags":["is_static","is_decorated"],"fullname":"fluxflow.config.ModelConfig.__mypy-replace","name":"__mypy-replace","original_first_arg":"__pydantic_extra__","type":{".class":"CallableType","arg_kinds":[5,5,5,5,5,5,5,5],"arg_names":["__pydantic_extra__","__pydantic_fields_set__","__pydantic_private__","vae_dim","feature_maps_dim","feature_maps_dim_disc","text_embedding_dim","pretrained_bert_model"],"arg_types":[{".class":"UnionType","items":[{".class":"Instance","args":["builtins.str",{".class":"AnyType","missing_import_name":null,"source_any":null,"type_of_any":2}],"extra_attrs":null,"type_ref":"builtins.dict"},{".class":"NoneType"}],"uses_pep604_syntax":false},{".class":"Instance","args":["builtins.str"],"extra_attrs":null,"type_ref":"builtins.set"},{".class":"UnionType","items":[{".class":"Instance","args":["builtins.str",{".class":"AnyType","missing_import_name":null,"source_any":null,"type_of_any":2}],"extra_attrs":null,"type_ref":"builtins.dict"},{".class":"NoneType"}],"uses_pep604_syntax":false},"builtins.int","builtins.int","builtins.int","builtins.int",{".class":"UnionType","items":["builtins.str",{".class":"NoneType"}],"uses_pep604_syntax":false}],"fallback":"builtins.function","from_concatenate":false,"implicit":false,"imprecise_arg_kinds":false,"is_bound":false,"is_ellipsis_args":false,"name":"__mypy-replace of ModelConfig","ret_type":{".class":"NoneType"},"type_guard":null,"type_is":null,"unpack_kwargs":false,"variables":[]}},"is_overload":false,"var":{".class":"Var","flags":["is_staticmethod","is_ready"],"fullname":"fluxflow.config.ModelConfig.__mypy-replace","name":"__mypy-replace","setter_type":null,"type":{".class":"CallableType","arg_kinds":[5,5,5,5,5,5,5,5],"arg_names":["__pydantic_extra__","__pydantic_fields_set__","__pydantic_private__","vae_dim","feature_maps_dim","feature_maps_dim_disc","text_embedding_dim","pretrained_bert_model"],"arg_types":[{".class":"UnionType","items":[{".class":"Instance","args":["builtins.str",{".class":"AnyType","missing_import_name":null,"source_any":null,"type_of_any":2}],"extra_attrs":null,"type_ref":"builtins.dict"},{".class":"NoneType"}],"uses_pep604_syntax":false},{".class":"Instance","args":["builtins.str"],"extra_attrs":null,"type_ref":"builtins.set"},{".class":"UnionType","items":[{".class":"Instance","args":["builtins.str",{".class":"AnyType","missing_import_name":null,"source_any":null,"type_of_any":2}],"extra_attrs":null,"type_ref":"builtins.dict"},{".class":"NoneType"}],"uses_pep604_syntax":false},"builtins.int","builtins.int","builtins.int","builtins.int",{".class":"UnionType","items":["builtins.str",{".class":"NoneType"}],"uses_pep604_syntax":false}],"fallback":"builtins.function","from_concatenate":false,"implicit":false,"imprecise_arg_kinds":false,"is_bound":false,"is_ellipsis_args":false,"name":"__mypy-replace of ModelConfig","ret_type":{".class":"NoneType"},"type_guard":null,"type_is":null,"unpack_kwargs":false,"variables":[]}}},"plugin_generated":true},"feature_maps_dim":{".class":"SymbolTableNode","kind":"Mdef","node":{".class":"Var","flags":["is_initialized_in_class","is_ready","has_explicit_value"],"fullname":"fluxflow.config.ModelConfig.feature_maps_dim","name":"feature_maps_dim","setter_type":null,"type":"builtins.int"}},"feature_maps_dim_disc":{".class":"SymbolTableNode","kind":"Mdef","node":{".class":"Var","flags":["is_initialized_in_class","is_ready","has_explicit_value"],"fullname":"fluxflow.config.ModelConfig.feature_maps_dim_disc","name":"feature_maps_dim_disc","setter_type":null,"type":"builtins.int"}},"pretrained_bert_model":{".class":"SymbolTableNode","kind":"Mdef","node":{".class":"Var","flags":["is_initialized_in_class","is_ready","has_explicit_value"],"fullname":"fluxflow.config.ModelConfig.pretrained_bert_model","name":"pretrained_bert_model","setter_type":null,"type":{".class":"UnionType","items":["builtins.str",{".class":"NoneType"}],"uses_pep604_syntax":false}}},"text_embedding_dim":{".class":"SymbolTableNode","kind":"Mdef","node":{".class":"Var","flags":["is_initialized_in_class","is_ready","has_explicit_value"],"fullname":"fluxflow.config.ModelConfig.text_embedding_dim","name":"text_embedding_dim","setter_type":null,"type":"builtins.int"}},"vae_dim":{".class":"SymbolTableNode","kind":"Mdef","node":{".class":"Var","flags":["is_initialized_in_class","is_ready","has_explicit_value"],"fullname":"fluxflow.config.ModelConfig.vae_dim","name":"vae_dim","setter_type":null,"type":"builtins.int"}}},"self_type":{".class":"TypeVarType","default":{".class":"AnyType","missing_import_name":null,"source_any":null,"type_of_any":4},"fullname":"fluxflow.config.ModelConfig.Self","id":0,"name":"Self","namespace":"","upper_bound":"fluxflow.config.ModelConfig","values":[],"variance":0},"slots":null,"tuple_type":null,"type_vars":[],"typeddict_type":null}},"OptimizationConfig":{".class":"SymbolTableNode","kind":"Gdef","node":{".class":"TypeInfo","_promote":[],"abstract_attributes":[],"alt_promote":null,"bases":["pydantic.main.BaseModel"],"dataclass_transform_spec":null,"declared_metaclass":null,"defn":{".class":"ClassDef","fullname":"fluxflow.config.OptimizationConfig","name":"OptimizationConfig","type_vars":[]},"deletable_attributes":[],"deprecated":null,"flags":[],"fullname":"fluxflow.config.OptimizationConfig","has_param_spec_type":false,"metaclass_type":"pydantic._internal._model_construction.ModelMetaclass","metadata":{"dataclass":{"attributes":[{"alias":null,"column":4,"has_default":false,"is_in_init":false,"is_init_var":false,"is_neither_frozen_nor_nonfrozen":true,"kw_only":true,"line":214,"name":"__pydantic_extra__","type":{".class":"UnionType","items":[{".class":"Instance","args":["builtins.str",{".class":"AnyType","missing_import_name":null,"source_any":null,"type_of_any":2}],"extra_attrs":null,"type_ref":"builtins.dict"},{".class":"NoneType"}],"uses_pep604_syntax":true}},{"alias":null,"column":4,"has_default":false,"is_in_init":false,"is_init_var":false,"is_neither_frozen_nor_nonfrozen":true,"kw_only":true,"line":217,"name":"__pydantic_fields_set__","type":{".class":"Instance","args":["builtins.str"],"extra_attrs":null,"type_ref":"builtins.set"}},{"alias":null,"column":4,"has_default":false,"is_in_init":false,"is_init_var":false,"is_neither_frozen_nor_nonfrozen":true,"kw_only":true,"line":220,"name":"__pydantic_private__","type":{".class":"UnionType","items":[{".class":"Instance","args":["builtins.str",{".class":"AnyType","missing_import_name":null,"source_any":null,"type_of_any":2}],"extra_attrs":null,"type_ref":"builtins.dict"},{".class":"NoneType"}],"uses_pep604_syntax":true}},{"alias":null,"column":4,"has_default":true,"is_in_init":true,"is_init_var":false,"is_neither_frozen_nor_nonfrozen":false,"kw_only":true,"line":101,"name":"optim_sched_config","type":{".class":"UnionType","items":["builtins.str",{".class":"NoneType"}],"uses_pep604_syntax":false}}],"frozen":false},"dataclass_tag":{}},"module_name":"fluxflow.config","mro":["fluxflow.config.OptimizationConfig","pydantic.main.BaseModel","builtins.object"],"names":{".class":"SymbolTable","__dataclass_fields__":{".class":"SymbolTableNode","kind":"Mdef","node":{".class":"Var","flags":["is_classvar","is_ready"],"fullname":"fluxflow.config.OptimizationConfig.__dataclass_fields__","name":"__dataclass_fields__","setter_type":null,"type":{".class":"Instance","args":["builtins.str",{".class":"AnyType","missing_import_name":null,"source_any":null,"type_of_any":2}],"extra_attrs":null,"type_ref":"builtins.dict"}},"plugin_generated":true},"__init__":{".class":"SymbolTableNode","kind":"Mdef","node":{".class":"FuncDef","abstract_status":0,"arg_kinds":[0,5],"arg_names":["self","optim_sched_config"],"dataclass_transform_spec":null,"deprecated":null,"flags":[],"fullname":"fluxflow.config.OptimizationConfig.__init__","name":"__init__","original_first_arg":"self","type":{".class":"CallableType","arg_kinds":[0,5],"arg_names":["self","optim_sched_config"],"arg_types":["fluxflow.config.OptimizationConfig",{".class":"UnionType","items":["builtins.str",{".class":"NoneType"}],"uses_pep604_syntax":false}],"fallback":"builtins.function","from_concatenate":false,"implicit":false,"imprecise_arg_kinds":false,"is_bound":false,"is_ellipsis_args":false,"name":"__init__ of OptimizationConfig","ret_type":{".class":"NoneType"},"type_guard":null,"type_is":null,"unpack_kwargs":false,"variables":[]}},"plugin_generated":true},"__match_args__":{".class":"SymbolTableNode","kind":"Mdef","node":{".class":"Var","flags":["is_ready","allow_incompatible_override"],"fullname":"fluxflow.config.OptimizationConfig.__match_args__","name":"__match_args__","setter_type":null,"type":{".class":"TupleType","implicit":false,"items":[],"partial_fallback":{".class":"Instance","args":[{".class":"AnyType","missing_import_name":null,"source_any":null,"type_of_any":6}],"extra_attrs":null,"type_ref":"builtins.tuple"}}},"plugin_generated":true},"__mypy-replace":{".class":"SymbolTableNode","kind":"Mdef","node":{".class":"Decorator","func":{".class":"FuncDef","abstract_status":0,"arg_kinds":[5,5,5,5],"arg_names":["__pydantic_extra__","__pydantic_fields_set__","__pydantic_private__","optim_sched_config"],"dataclass_transform_spec":null,"deprecated":null,"flags":["is_static","is_decorated"],"fullname":"fluxflow.config.OptimizationConfig.__mypy-replace","name":"__mypy-replace","original_first_arg":"__pydantic_extra__","type":{".class":"CallableType","arg_kinds":[5,5,5,5],"arg_names":["__pydantic_extra__","__pydantic_fields_set__","__pydantic_private__","optim_sched_config"],"arg_types":[{".class":"UnionType","items":[{".class":"Instance","args":["builtins.str",{".class":"AnyType","missing_import_name":null,"source_any":null,"type_of_any":2}],"extra_attrs":null,"type_ref":"builtins.dict"},{".class":"NoneType"}],"uses_pep604_syntax":false},{".class":"Instance","args":["builtins.str"],"extra_attrs":null,"type_ref":"builtins.set"},{".class":"UnionType","items":[{".class":"Instance","args":["builtins.str",{".class":"AnyType","missing_import_name":null,"source_any":null,"type_of_any":2}],"extra_attrs":null,"type_ref":"builtins.dict"},{".class":"NoneType"}],"uses_pep604_syntax":false},{".class":"UnionType","items":["builtins.str",{".class":"NoneType"}],"uses_pep604_syntax":false}],"fallback":"builtins.function","from_concatenate":false,"implicit":false,"imprecise_arg_kinds":false,"is_bound":false,"is_ellipsis_args":false,"name":"__mypy-replace of OptimizationConfig","ret_type":{".class":"NoneType"},"type_guard":null,"type_is":null,"unpack_kwargs":false,"variables":[]}},"is_overload":false,"var":{".class":"Var","flags":["is_staticmethod","is_ready"],"fullname":"fluxflow.config.OptimizationConfig.__mypy-replace","name":"__mypy-replace","setter_type":null,"type":{".class":"CallableType","arg_kinds":[5,5,5,5],"arg_names":["__pydantic_extra__","__pydantic_fields_set__","__pydantic_private__","optim_sched_config"],"arg_types":[{".class":"UnionType","items":[{".class":"Instance","args":["builtins.str",{".class":"AnyType","missing_import_name":null,"source_any":null,"type_of_any":2}],"extra_attrs":null,"type_ref":"builtins.dict"},{".class":"NoneType"}],"uses_pep604_syntax":false},{".class":"Instance","args":["builtins.str"],"extra_attrs":null,"type_ref":"builtins.set"},{".class":"UnionType","items":[{".class":"Instance","args":["builtins.str",{".class":"AnyType","missing_import_name":null,"source_any":null,"type_of_any":2}],"extra_attrs":null,"type_ref":"builtins.dict"},{".class":"NoneType"}],"uses_pep604_syntax":false},{".class":"UnionType","items":["builtins.str",{".class":"NoneType"}],"uses_pep604_syntax":false}],"fallback":"builtins.function","from_concatenate":false,"implicit":false,"imprecise_arg_kinds":false,"is_bound":false,"is_ellipsis_args":false,"name":"__mypy-replace of OptimizationConfig","ret_type":{".class":"NoneType"},"type_guard":null,"type_is":null,"unpack_kwargs":false,"variables":[]}}},"plugin_generated":true},"optim_sched_config":{".class":"SymbolTableNode","kind":"Mdef","node":{".class":"Var","flags":["is_initialized_in_class","is_ready","has_explicit_value"],"fullname":"fluxflow.config.OptimizationConfig.optim_sched_config","name":"optim_sched_config","setter_type":null,"type":{".class":"UnionType","items":["builtins.str",{".class":"NoneType"}],"uses_pep604_syntax":false}}}},"self_type":{".class":"TypeVarType","default":{".class":"AnyType","missing_import_name":null,"source_any":null,"type_of_any":4},"fullname":"fluxflow.config.OptimizationConfig.Self","id":0,"name":"Self","namespace":"","upper_bound":"fluxflow.config.OptimizationConfig","values":[],"variance":0},"slots":null,"tuple_type":null,"type_vars":[],"typeddict_type":null}},"Optional":{".class":"SymbolTableNode","cross_ref":"typing.Optional","kind":"Gdef"},"OutputConfig":{".class":"SymbolTableNode","kind":"Gdef","node":{".class":"TypeInfo","_promote":[],"abstract_attributes":[],"alt_promote":null,"bases":["pydantic.main.BaseModel"],"dataclass_transform_spec":null,"declared_metaclass":null,"defn":{".class":"ClassDef","fullname":"fluxflow.config.OutputConfig","name":"OutputConfig","type_vars":[]},"deletable_attributes":[],"deprecated":null,"flags":[],"fullname":"fluxflow.config.OutputConfig","has_param_spec_type":false,"metaclass_type":"pydantic._internal._model_construction.ModelMetaclass","metadata":{"dataclass":{"attributes":[{"alias":null,"column":4,"has_default":false,"is_in_init":false,"is_init_var":false,"is_neither_frozen_nor_nonfrozen":true,"kw_only":true,"line":214,"name":"__pydantic_extra__","type":{".class":"UnionType","items":[{".class":"Instance","args":["builtins.str",{".class":"AnyType","missing_import_name":null,"source_any":null,"type_of_any":2}],"extra_attrs":null,"type_ref":"builtins.dict"},{".class":"NoneType"}],"uses_pep604_syntax":true}},{"alias":null,"column":4,"has_default":false,"is_in_init":false,"is_init_var":false,"is_neither_frozen_nor_nonfrozen":true,"kw_only":true,"line":217,"name":"__pydantic_fields_set__","type":{".class":"Instance","args":["builtins.str"],"extra_attrs":null,"type_ref":"builtins.set"}},{"alias":null,"column":4,"has_default":false,"is_in_init":false,"is_init_var":false,"is_neither_frozen_nor_nonfrozen":true,"kw_only":true,"line":220,"name":"__pydantic_private__","type":{".class":"UnionType","items":[{".class":"Instance","args":["builtins.str",{".class":"AnyType","missing_import_name":null,"source_any":null,"type_of_any":2}],"extra_attrs":null,"type_ref":"builtins.dict"},{".class":"NoneType"}],"uses_pep604_syntax":true}},{"alias":null,"column":4,"has_default":true,"is_in_init":true,"is_init_var":false,"is_neither_frozen_nor_nonfrozen":false,"kw_only":true,"line":109,"name":"output_path","type":"builtins.str"},{"alias":null,"column":4,"has_default":true,"is_in_init":true,"is_init_var":false,"is_neither_frozen_nor_nonfrozen":false,"kw_only":true,"line":110,"name":"log_interval","type":"builtins.int"},{"alias":null,"column":4,"has_default":true,"is_in_init":true,"is_init_var":false,"is_neither_frozen_nor_nonfrozen":false,"kw_only":true,"line":111,"name":"sample_interval","type":"builtins.int"},{"alias":null,"column":4,"has_default":true,"is_in_init":true,"is_init_var":false,"is_neither_frozen_nor_nonfrozen":false,"kw_only":true,"line":112,"name":"no_samples","type":"builtins.bool"},{"alias":null,"column":4,"has_default":true,"is_in_init":true,"is_init_var":false,"is_neither_frozen_nor_nonfrozen":false,"kw_only":true,"line":113,"name":"test_image_address","type":{".class":"Instance","args":["builtins.str"],"extra_attrs":null,"type_ref":"builtins.list"}},{"alias":null,"column":4,"has_default":true,"is_in_init":true,"is_init_var":false,"is_neither_frozen_nor_nonfrozen":false,"kw_only":true,"line":116,"name":"sample_captions","type":{".class":"Instance","args":["builtins.str"],"extra_attrs":null,"type_ref":"builtins.list"}},{"alias":null,"column":4,"has_default":true,"is_in_init":true,"is_init_var":false,"is_neither_frozen_nor_nonfrozen":false,"kw_only":true,"line":119,"name":"log_level","type":{".class":"UnionType","items":[{".class":"LiteralType","fallback":"builtins.str","value":"DEBUG"},{".class":"LiteralType","fallback":"builtins.str","value":"INFO"},{".class":"LiteralType","fallback":"builtins.str","value":"WARNING"},{".class":"LiteralType","fallback":"builtins.str","value":"ERROR"}],"uses_pep604_syntax":false}},{"alias":null,"column":4,"has_default":true,"is_in_init":true,"is_init_var":false,"is_neither_frozen_nor_nonfrozen":false,"kw_only":true,"line":122,"name":"log_file","type":{".class":"UnionType","items":["builtins.str",{".class":"NoneType"}],"uses_pep604_syntax":false}}],"frozen":false},"dataclass_tag":{}},"module_name":"fluxflow.config","mro":["fluxflow.config.OutputConfig","pydantic.main.BaseModel","builtins.object"],"names":{".class":"SymbolTable","__dataclass_fields__":{".class":"SymbolTableNode","kind":"Mdef","node":{".class":"Var","flags":["is_classvar","is_ready"],"fullname":"fluxflow.config.OutputConfig.__dataclass_fields__","name":"__dataclass_fields__","setter_type":null,"type":{".class":"Instance","args":["builtins.str",{".class":"AnyType","missing_import_name":null,"source_any":null,"type_of_any":2}],"extra_attrs":null,"type_ref":"builtins.dict"}},"plugin_generated":true},"__init__":{".class":"SymbolTableNode","kind":"Mdef","node":{".class":"FuncDef","abstract_status":0,"arg_kinds":[0,5,5,5,5,5,5,5,5],"arg_names":["self","output_path","log_interval","sample_interval","no_samples","test_image_address","sample_captions","log_level","log_file"],"dataclass_transform_spec":null,"deprecated":null,"flags":[],"fullname":"fluxflow.config.OutputConfig.__init__","name":"__init__","original_first_arg":"self","type":{".class":"CallableType","arg_kinds":[0,5,5,5,5,5,5,5,5],"arg_names":["self","output_path","log_interval","sample_interval","no_samples","test_image_address","sample_captions","log_level","log_file"],"arg_types":["fluxflow.config.OutputConfig","builtins.str","builtins.int","builtins.int","builtins.bool",{".class":"Instance","args":["builtins.str"],"extra_attrs":null,"type_ref":"builtins.list"},{".class":"Instance","args":["builtins.str"],"extra_attrs":null,"type_ref":"builtins.list"},{".class":"UnionType","items":[{".class":"LiteralType","fallback":"builtins.str","value":"DEBUG"},{".class":"LiteralType","fallback":"builtins.str","value":"INFO"},{".class":"LiteralType","fallback":"builtins.str","value":"WARNING"},{".class":"LiteralType","fallback":"builtins.str","value":"ERROR"}],"uses_pep604_syntax":false},{".class":"UnionType","items":["builtins.str",{".class":"NoneType"}],"uses_pep604_syntax":false}],"fallback":"builtins.function","from_concatenate":false,"implicit":false,"imprecise_arg_kinds":false,"is_bound":false,"is_ellipsis_args":false,"name":"__init__ of OutputConfig","ret_type":{".class":"NoneType"},"type_guard":null,"type_is":null,"unpack_kwargs":false,"variables":[]}},"plugin_generated":true},"__match_args__":{".class":"SymbolTableNode","kind":"Mdef","node":{".class":"Var","flags":["is_ready","allow_incompatible_override"],"fullname":"fluxflow.config.OutputConfig.__match_args__","name":"__match_args__","setter_type":null,"type":{".class":"TupleType","implicit":false,"items":[],"partial_fallback":{".class":"Instance","args":[{".class":"AnyType","missing_import_name":null,"source_any":null,"type_of_any":6}],"extra_attrs":null,"type_ref":"builtins.tuple"}}},"plugin_generated":true},"__mypy-replace":{".class":"SymbolTableNode","kind":"Mdef","node":{".class":"Decorator","func":{".class":"FuncDef","abstract_status":0,"arg_kinds":[5,5,5,5,5,5,5,5,5,5,5],"arg_names":["__pydantic_extra__","__pydantic_fields_set__","__pydantic_private__","output_path","log_interval","sample_interval","no_samples","test_image_address","sample_captions","log_level","log_file"],"dataclass_transform_spec":null,"deprecated":null,"flags":["is_static","is_decorated"],"fullname":"fluxflow.config.OutputConfig.__mypy-replace","name":"__mypy-replace","original_first_arg":"__pydantic_extra__","type":{".class":"CallableType","arg_kinds":[5,5,5,5,5,5,5,5,5,5,5],"arg_names":["__pydantic_extra__","__pydantic_fields_set__","__pydantic_private__","output_path","log_interval","sample_interval","no_samples","test_image_address","sample_captions","log_level","log_file"],"arg_types":[{".class":"UnionType","items":[{".class":"Instance","args":["builtins.str",{".class":"AnyType","missing_import_name":null,"source_any":null,"type_of_any":2}],"extra_attrs":null,"type_ref":"builtins.dict"},{".class":"NoneType"}],"uses_pep604_syntax":false},{".class":"Instance","args":["builtins.str"],"extra_attrs":null,"type_ref":"builtins.set"},{".class":"UnionType","items":[{".class":"Instance","args":["builtins.str",{".class":"AnyType","missing_import_name":null,"source_any":null,"type_of_any":2}],"extra_attrs":null,"type_ref":"builtins.dict"},{".class":"NoneType"}],"uses_pep604_syntax":false},"builtins.str","builtins.int","builtins.int","builtins.bool",{".class":"Instance","args":["builtins.str"],"extra_attrs":null,"type_ref":"builtins.list"},{".class":"Instance","args":["builtins.str"],"extra_attrs":null,"type_ref":"builtins.list"},{".class":"UnionType","items":[{".class":"LiteralType","fallback":"builtins.str","value":"DEBUG"},{".class":"LiteralType","fallback":"builtins.str","value":"INFO"},{".class":"LiteralType","fallback":"builtins.str","value":"WARNING"},{".class":"LiteralType","fallback":"builtins.str","value":"ERROR"}],"uses_pep604_syntax":false},{".class":"UnionType","items":["builtins.str",{".class":"NoneType"}],"uses_pep604_syntax":false}],"fallback":"builtins.function","from_concatenate":false,"implicit":false,"imprecise_arg_kinds":false,"is_bound":false,"is_ellipsis_args":false,"name":"__mypy-replace of OutputConfig","ret_type":{".class":"NoneType"},"type_guard":null,"type_is":null,"unpack_kwargs":false,"variables":[]}},"is_overload":false,"var":{".class":"Var","flags":["is_staticmethod","is_ready"],"fullname":"fluxflow.config.OutputConfig.__mypy-replace","name":"__mypy-replace","setter_type":null,"type":{".class":"CallableType","arg_kinds":[5,5,5,5,5,5,5,5,5,5,5],"arg_names":["__pydantic_extra__","__pydantic_fields_set__","__pydantic_private__","output_path","log_interval","sample_interval","no_samples","test_image_address","sample_captions","log_level","log_file"],"arg_types":[{".class":"UnionType","items":[{".class":"Instance","args":["builtins.str",{".class":"AnyType","missing_import_name":null,"source_any":null,"type_of_any":2}],"extra_attrs":null,"type_ref":"builtins.dict"},{".class":"NoneType"}],"uses_pep604_syntax":false},{".class":"Instance","args":["builtins.str"],"extra_attrs":null,"type_ref":"builtins.set"},{".class":"UnionType","items":[{".class":"Instance","args":["builtins.str",{".class":"AnyType","missing_import_name":null,"source_any":null,"type_of_any":2}],"extra_attrs":null,"type_ref":"builtins.dict"},{".class":"NoneType"}],"uses_pep604_syntax":false},"builtins.str","builtins.int","builtins.int","builtins.bool",{".class":"Instance","args":["builtins.str"],"extra_attrs":null,"type_ref":"builtins.list"},{".class":"Instance","args":["builtins.str"],"extra_attrs":null,"type_ref":"builtins.list"},{".class":"UnionType","items":[{".class":"LiteralType","fallback":"builtins.str","value":"DEBUG"},{".class":"LiteralType","fallback":"builtins.str","value":"INFO"},{".class":"LiteralType","fallback":"builtins.str","value":"WARNING"},{".class":"LiteralType","fallback":"builtins.str","value":"ERROR"}],"uses_pep604_syntax":false},{".class":"UnionType","items":["builtins.str",{".class":"NoneType"}],"uses_pep604_syntax":false}],"fallback":"builtins.function","from_concatenate":false,"implicit":false,"imprecise_arg_kinds":false,"is_bound":false,"is_ellipsis_args":false,"name":"__mypy-replace of OutputConfig","ret_type":{".class":"NoneType"},"type_guard":null,"type_is":null,"unpack_kwargs":false,"variables":[]}}},"plugin_generated":true},"log_file":{".class":"SymbolTableNode","kind":"Mdef","node":{".class":"Var","flags":["is_initialized_in_class","is_ready","has_explicit_value"],"fullname":"fluxflow.config.OutputConfig.log_file","name":"log_file","setter_type":null,"type":{".class":"UnionType","items":["builtins.str",{".class":"NoneType"}],"uses_pep604_syntax":false}}},"log_interval":{".class":"SymbolTableNode","kind":"Mdef","node":{".class":"Var","flags":["is_initialized_in_class","is_ready","has_explicit_value"],"fullname":"fluxflow.config.OutputConfig.log_interval","name":"log_interval","setter_type":null,"type":"builtins.int"}},"log_level":{".class":"SymbolTableNode","kind":"Mdef","node":{".class":"Var","flags":["is_initialized_in_class","is_ready","has_explicit_value"],"fullname":"fluxflow.config.OutputConfig.log_level","name":"log_level","setter_type":null,"type":{".class":"UnionType","items":[{".class":"LiteralType","fallback":"builtins.str","value":"DEBUG"},{".class":"LiteralType","fallback":"builtins.str","value":"INFO"},{".class":"LiteralType","fallback":"builtins.str","value":"WARNING"},{".class":"LiteralType","fallback":"builtins.str","value":"ERROR"}],"uses_pep604_syntax":false}}},"no_samples":{".class":"SymbolTableNode","kind":"Mdef","node":{".class":"Var","flags":["is_initialized_in_class","is_ready","has_explicit_value"],"fullname":"fluxflow.config.OutputConfig.no_samples","name":"no_samples","setter_type":null,"type":"builtins.bool"}},"output_path":{".class":"SymbolTableNode","kind":"Mdef","node":{".class":"Var","flags":["is_initialized_in_class","is_ready","has_explicit_value"],"fullname":"fluxflow.config.OutputConfig.output_path","name":"output_path","setter_type":null,"type":"builtins.str"}},"sample_captions":{".class":"SymbolTableNode","kind":"Mdef","node":{".class":"Var","flags":["is_initialized_in_class","is_ready","has_explicit_value"],"fullname":"fluxflow.config.OutputConfig.sample_captions","name":"sample_captions","setter_type":null,"type":{".class":"Instance","args":["builtins.str"],"extra_attrs":null,"type_ref":"builtins.list"}}},"sample_interval":{".class":"SymbolTableNode","kind":"Mdef","node":{".class":"Var","flags":["is_initialized_in_class","is_ready","has_explicit_value"],"fullname":"fluxflow.config.OutputConfig.sample_interval","name":"sample_interval","setter_type":null,"type":"builtins.int"}},"test_image_address":{".class":"SymbolTableNode","kind":"Mdef","node":{".class":"Var","flags":["is_initialized_in_class","is_ready","has_explicit_value"],"fullname":"fluxflow.config.OutputConfig.test_image_address","name":"test_image_address","setter_type":null,"type":{".class":"Instance","args":["builtins.str"],"extra_attrs":null,"type_ref":"builtins.list"}}}},"self_type":{".class":"TypeVarType","default":{".class":"AnyType","missing_import_name":null,"source_any":null,"type_of_any":4},"fullname":"fluxflow.config.OutputConfig.Self","id":0,"name":"Self","namespace":"","upper_bound":"fluxflow.config.OutputConfig","values":[],"variance":0},"slots":null,"tuple_type":null,"type_vars":[],"typeddict_type":null}},"Path":{".class":"SymbolTableNode","cross_ref":"pathlib.Path","kind":"Gdef"},"TrainingConfig":{".class":"SymbolTableNode","kind":"Gdef","node":{".class":"TypeInfo","_promote":[],"abstract_attributes":[],"alt_promote":null,"bases":["pydantic.main.BaseModel"],"dataclass_transform_spec":null,"declared_metaclass":null,"defn":{".class":"ClassDef","fullname":"fluxflow.config.TrainingConfig","name":"TrainingConfig","type_vars":[]},"deletable_attributes":[],"deprecated":null,"flags":[],"fullname":"fluxflow.config.TrainingConfig","has_param_spec_type":false,"metaclass_type":"pydantic._internal._model_construction.ModelMetaclass","metadata":{"dataclass":{"attributes":[{"alias":null,"column":4,"has_default":false,"is_in_init":false,"is_init_var":false,"is_neither_frozen_nor_nonfrozen":true,"kw_only":true,"line":214,"name":"__pydantic_extra__","type":{".class":"UnionType","items":[{".class":"Instance","args":["builtins.str",{".class":"AnyType","missing_import_name":null,"source_any":null,"type_of_any":2}],"extra_attrs":null,"type_ref":"builtins.dict"},{".class":"NoneType"}],"uses_pep604_syntax":true}},{"alias":null,"column":4,"has_default":false,"is_in_init":false,"is_init_var":false,"is_neither_frozen_nor_nonfrozen":true,"kw_only":true,"line":217,"name":"__pydantic_fields_set__","type":{".class":"Instance","args":["builtins.str"],"extra_attrs":null,"type_ref":"builtins.set"}},{"alias":null,"column":4,"has_default":false,"is_in_init":false,"is_init_var":false,"is_neither_frozen_nor_nonfrozen":true,"kw_only":true,"line":220,"name":"__pydantic_private__","type":{".class":"UnionType","items":[{".class":"Instance","args":["builtins.str",{".class":"AnyType","missing_import_name":null,"source_any":null,"type_of_any":2}],"extra_attrs":null,"type_ref":"builtins.dict"},{".class":"NoneType"}],"uses_pep604_syntax":true}},{"alias":null,"column":4,"has_default":true,"is_in_init":true,"is_init_var":false,"is_neither_frozen_nor_nonfrozen":false,"kw_only":true,"line":68,"name":"n_epochs","type":"builtins.int"},{"alias":null,"column":4,"has_default":true,"is_in_init":true,"is_init_var":false,"is_neither_frozen_nor_nonfrozen":false,"kw_only":true,"line":69,"name":"batch_size","type":"builtins.int"},{"alias":null,"column":4,"has_default":true,"is_in_init":true,"is_init_var":false,"is_neither_frozen_nor_nonfrozen":false,"kw_only":true,"line":70,"name":"workers","type":"builtins.int"},{"alias":null,"column":4,"has_default":true,"is_in_init":true,"is_init_var":false,"is_neither_frozen_nor_nonfrozen":false,"kw_only":true,"line":71,"name":"lr","type":"builtins.float"},{"alias":null,"column":4,"has_default":true,"is_in_init":true,"is_init_var":false,"is_neither_frozen_nor_nonfrozen":false,"kw_only":true,"line":72,"name":"lr_min","type":"builtins.float"},{"alias":null,"column":4,"has_default":true,"is_in_init":true,"is_init_var":false,"is_neither_frozen_nor_nonfrozen":false,"kw_only":true,"line":75,"name":"training_steps","type":"builtins.int"},{"alias":null,"column":4,"has_default":true,"is_in_init":true,"is_init_var":false,"is_neither_frozen_nor_nonfrozen":false,"kw_only":true,"line":76,"name":"use_fp16","type":"builtins.bool"},{"alias":null,"column":4,"has_default":true,"is_in_init":true,"is_init_var":false,"is_neither_frozen_nor_nonfrozen":false,"kw_only":true,"line":77,"name":"initial_clipping_norm","type":"builtins.float"},{"alias":null,"column":4,"has_default":true,"is_in_init":true,"is_init_var":false,"is_neither_frozen_nor_nonfrozen":false,"kw_only":true,"line":78,"name":"preserve_lr","type":"builtins.bool"},{"alias":null,"column":4,"has_default":true,"is_in_init":true,"is_init_var":false,"is_neither_frozen_nor_nonfrozen":false,"kw_only":true,"line":83,"name":"train_vae","type":"builtins.bool"},{"alias":null,"column":4,"has_default":true,"is_in_init":true,"is_init_var":false,"is_neither_frozen_nor_nonfrozen":false,"kw_only":true,"line":84,"name":"train_no_gan","type":"builtins.bool"},{"alias":null,"column":4,"has_default":true,"is_in_init":true,"is_init_var":false,"is_neither_frozen_nor_nonfrozen":false,"kw_only":true,"line":85,"name":"train_spade","type":"builtins.bool"},{"alias":null,"column":4,"has_default":true,"is_in_init":true,"is_init_var":false,"is_neither_frozen_nor_nonfrozen":false,"kw_only":true,"line":86,"name":"train_diff","type":"builtins.bool"},{"alias":null,"column":4,"has_default":true,"is_in_init":true,"is_init_var":false,"is_neither_frozen_nor_nonfrozen":false,"kw_only":true,"line":87,"name":"train_diff_full","type":"builtins.bool"},{"alias":null,"column":4,"has_default":true,"is_in_init":true,"is_init_var":false,"is_neither_frozen_nor_nonfrozen":false,"kw_only":true,"line":90,"name":"kl_beta","type":"builtins.float"},{"alias":null,"column":4,"has_default":true,"is_in_init":true,"is_init_var":false,"is_neither_frozen_nor_nonfrozen":false,"kw_only":true,"line":91,"name":"kl_warmup_steps","type":"builtins.int"},{"alias":null,"column":4,"has_default":true,"is_in_init":true,"is_init_var":false,"is_neither_frozen_nor_nonfrozen":false,"kw_only":true,"line":92,"name":"kl_free_bits","type":"builtins.float"},{"alias":null,"column":4,"has_default":true,"is_in_init":true,"is_init_var":false,"is_neither_frozen_nor_nonfrozen":false,"kw_only":true,"line":95,"name":"lambda_adv","type":"builtins.float"}],"frozen":false},"dataclass_tag":{}},"module_name":"fluxflow.config","mro":["fluxflow.config.TrainingConfig","pydantic.main.BaseModel","builtins.object"],"names":{".class":"SymbolTable","__dataclass_fields__":{".class":"SymbolTableNode","kind":"Mdef","node":{".class":"Var","flags":["is_classvar","is_ready"],"fullname":"fluxflow.config.TrainingConfig.__dataclass_fields__","name":"__dataclass_fields__","setter_type":null,"type":{".class":"Instance","args":["builtins.str",{".class":"AnyType","missing_import_name":null,"source_any":null,"type_of_any":2}],"extra_attrs":null,"type_ref":"builtins.dict"}},"plugin_generated":true},"__init__":{".class":"SymbolTableNode","kind":"Mdef","node":{".class":"FuncDef","abstract_status":0,"arg_kinds":[0,5,5,5,5,5,5,5,5,5,5,5,5,5,5,5,5,5,5],"arg_names":["self","n_epochs","batch_size","workers","lr","lr_min","training_steps","use_fp16","initial_clipping_norm","preserve_lr","train_vae","train_no_gan","train_spade","train_diff","train_diff_full","kl_beta","kl_warmup_steps","kl_free_bits","lambda_adv"],"dataclass_transform_spec":null,"deprecated":null,"flags":[],"fullname":"fluxflow.config.TrainingConfig.__init__","name":"__init__","original_first_arg":"self","type":{".class":"CallableType","arg_kinds":[0,5,5,5,5,5,5,5,5,5,5,5,5,5,5,5,5,5,5],"arg_names":["self","n_epochs","batch_size","workers","lr","lr_min","training_steps","use_fp16","initial_clipping_norm","preserve_lr","train_vae","train_no_gan","train_spade","train_diff","train_diff_full","kl_beta","kl_warmup_steps","kl_free_bits","lambda_adv"],"arg_types":["fluxflow.config.TrainingConfig","builtins.int","builtins.int","builtins.int","builtins.float","builtins.float","builtins.int","builtins.bool","builtins.float","builtins.bool","builtins.bool","builtins.bool","builtins.bool","builtins.bool","builtins.bool","builtins.float","builtins.int","builtins.float","builtins.float"],"fallback":"builtins.function","from_concatenate":false,"implicit":false,"imprecise_arg_kinds":false,"is_bound":false,"is_ellipsis_args":false,"name":"__init__ of TrainingConfig","ret_type":{".class":"NoneType"},"type_guard":null,"type_is":null,"unpack_kwargs":false,"variables":[]}},"plugin_generated":true},"__match_args__":{".class":"SymbolTableNode","kind":"Mdef","node":{".class":"Var","flags":["is_ready","allow_incompatible_override"],"fullname":"fluxflow.config.TrainingConfig.__match_args__","name":"__match_args__","setter_type":null,"type":{".class":"TupleType","implicit":false,"items":[],"partial_fallback":{".class":"Instance","args":[{".class":"AnyType","missing_import_name":null,"source_any":null,"type_of_any":6}],"extra_attrs":null,"type_ref":"builtins.tuple"}}},"plugin_generated":true},"__mypy-replace":{".class":"SymbolTableNode","kind":"Mdef","node":{".class":"Decorator","func":{".class":"FuncDef","abstract_status":0,"arg_kinds":[5,5,5,5,5,5,5,5,5,5,5,5,5,5,5,5,5,5,5,5,5],"arg_names":["__pydantic_extra__","__pydantic_fields_set__","__pydantic_private__","n_epochs","batch_size","workers","lr","lr_min","training_steps","use_fp16","initial_clipping_norm","preserve_lr","train_vae","train_no_gan","train_spade","train_diff","train_diff_full","kl_beta","kl_warmup_steps","kl_free_bits","lambda_adv"],"dataclass_transform_spec":null,"deprecated":null,"flags":["is_static","is_decorated"],"fullname":"fluxflow.config.TrainingConfig.__mypy-replace","name":"__mypy-replace","original_first_arg":"__pydantic_extra__","type":{".class":"CallableType","arg_kinds":[5,5,5,5,5,5,5,5,5,5,5,5,5,5,5,5,5,5,5,5,5],"arg_names":["__pydantic_extra__","__pydantic_fields_set__","__pydantic_private__","n_epochs","batch_size","workers","lr","lr_min","training_steps","use_fp16","initial_clipping_norm","preserve_lr","train_vae","train_no_gan","train_spade","train_diff","train_diff_full","kl_beta","kl_warmup_steps","kl_free_bits","lambda_adv"],"arg_types":[{".class":"UnionType","items":[{".class":"Instance","args":["builtins.str",{".class":"AnyType","missing_import_name":null,"source_any":null,"type_of_any":2}],"extra_attrs":null,"type_ref":"builtins.dict"},{".class":"NoneType"}],"uses_pep604_syntax":false},{".class":"Instance","args":["builtins.str"],"extra_attrs":null,"type_ref":"builtins.set"},{".class":"UnionType","items":[{".class":"Instance","args":["builtins.str",{".class":"AnyType","missing_import_name":null,"source_any":null,"type_of_any":2}],"extra_attrs":null,"type_ref":"builtins.dict"},{".class":"NoneType"}],"uses_pep604_syntax":false},"builtins.int","builtins.int","builtins.int","builtins.float","builtins.float","builtins.int","builtins.bool","builtins.float","builtins.bool","builtins.bool","builtins.bool","builtins.bool","builtins.bool","builtins.bool","builtins.float","builtins.int","builtins.float","builtins.float"],"fallback":"builtins.function","from_concatenate":false,"implicit":false,"imprecise_arg_kinds":false,"is_bound":false,"is_ellipsis_args":false,"name":"__mypy-replace of TrainingConfig","ret_type":{".class":"NoneType"},"type_guard":null,"type_is":null,"unpack_kwargs":false,"variables":[]}},"is_overload":false,"var":{".class":"Var","flags":["is_staticmethod","is_ready"],"fullname":"fluxflow.config.TrainingConfig.__mypy-replace","name":"__mypy-replace","setter_type":null,"type":{".class":"CallableType","arg_kinds":[5,5,5,5,5,5,5,5,5,5,5,5,5,5,5,5,5,5,5,5,5],"arg_names":["__pydantic_extra__","__pydantic_fields_set__","__pydantic_private__","n_epochs","batch_size","workers","lr","lr_min","training_steps","use_fp16","initial_clipping_norm","preserve_lr","train_vae","train_no_gan","train_spade","train_diff","train_diff_full","kl_beta","kl_warmup_steps","kl_free_bits","lambda_adv"],"arg_types":[{".class":"UnionType","items":[{".class":"Instance","args":["builtins.str",{".class":"AnyType","missing_import_name":null,"source_any":null,"type_of_any":2}],"extra_attrs":null,"type_ref":"builtins.dict"},{".class":"NoneType"}],"uses_pep604_syntax":false},{".class":"Instance","args":["builtins.str"],"extra_attrs":null,"type_ref":"builtins.set"},{".class":"UnionType","items":[{".class":"Instance","args":["builtins.str",{".class":"AnyType","missing_import_name":null,"source_any":null,"type_of_any":2}],"extra_attrs":null,"type_ref":"builtins.dict"},{".class":"NoneType"}],"uses_pep604_syntax":false},"builtins.int","builtins.int","builtins.int","builtins.float","builtins.float","builtins.int","builtins.bool","builtins.float","builtins.bool","builtins.bool","builtins.bool","builtins.bool","builtins.bool","builtins.bool","builtins.float","builtins.int","builtins.float","builtins.float"],"fallback":"builtins.function","from_concatenate":false,"implicit":false,"imprecise_arg_kinds":false,"is_bound":false,"is_ellipsis_args":false,"name":"__mypy-replace of TrainingConfig","ret_type":{".class":"NoneType"},"type_guard":null,"type_is":null,"unpack_kwargs":false,"variables":[]}}},"plugin_generated":true},"batch_size":{".class":"SymbolTableNode","kind":"Mdef","node":{".class":"Var","flags":["is_initialized_in_class","is_ready","has_explicit_value"],"fullname":"fluxflow.config.TrainingConfig.batch_size","name":"batch_size","setter_type":null,"type":"builtins.int"}},"initial_clipping_norm":{".class":"SymbolTableNode","kind":"Mdef","node":{".class":"Var","flags":["is_initialized_in_class","is_ready","has_explicit_value"],"fullname":"fluxflow.config.TrainingConfig.initial_clipping_norm","name":"initial_clipping_norm","setter_type":null,"type":"builtins.float"}},"kl_beta":{".class":"SymbolTableNode","kind":"Mdef","node":{".class":"Var","flags":["is_initialized_in_class","is_ready","has_explicit_value"],"fullname":"fluxflow.config.TrainingConfig.kl_beta","name":"kl_beta","setter_type":null,"type":"builtins.float"}},"kl_free_bits":{".class":"SymbolTableNode","kind":"Mdef","node":{".class":"Var","flags":["is_initialized_in_class","is_ready","has_explicit_value"],"fullname":"fluxflow.config.TrainingConfig.kl_free_bits","name":"kl_free_bits","setter_type":null,"type":"builtins.float"}},"kl_warmup_steps":{".class":"SymbolTableNode","kind":"Mdef","node":{".class":"Var","flags":["is_initialized_in_class","is_ready","has_explicit_value"],"fullname":"fluxflow.config.TrainingConfig.kl_warmup_steps","name":"kl_warmup_steps","setter_type":null,"type":"builtins.int"}},"lambda_adv":{".class":"SymbolTableNode","kind":"Mdef","node":{".class":"Var","flags":["is_initialized_in_class","is_ready","has_explicit_value"],"fullname":"fluxflow.config.TrainingConfig.lambda_adv","name":"lambda_adv","setter_type":null,"type":"builtins.float"}},"lr":{".class":"SymbolTableNode","kind":"Mdef","node":{".class":"Var","flags":["is_initialized_in_class","is_ready","has_explicit_value"],"fullname":"fluxflow.config.TrainingConfig.lr","name":"lr","setter_type":null,"type":"builtins.float"}},"lr_min":{".class":"SymbolTableNode","kind":"Mdef","node":{".class":"Var","flags":["is_initialized_in_class","is_ready","has_explicit_value"],"fullname":"fluxflow.config.TrainingConfig.lr_min","name":"lr_min","setter_type":null,"type":"builtins.float"}},"n_epochs":{".class":"SymbolTableNode","kind":"Mdef","node":{".class":"Var","flags":["is_initialized_in_class","is_ready","has_explicit_value"],"fullname":"fluxflow.config.TrainingConfig.n_epochs","name":"n_epochs","setter_type":null,"type":"builtins.int"}},"preserve_lr":{".class":"SymbolTableNode","kind":"Mdef","node":{".class":"Var","flags":["is_initialized_in_class","is_ready","has_explicit_value"],"fullname":"fluxflow.config.TrainingConfig.preserve_lr","name":"preserve_lr","setter_type":null,"type":"builtins.bool"}},"train_diff":{".class":"SymbolTableNode","kind":"Mdef","node":{".class":"Var","flags":["is_initialized_in_class","is_ready","has_explicit_value"],"fullname":"fluxflow.config.TrainingConfig.train_diff","name":"train_diff","setter_type":null,"type":"builtins.bool"}},"train_diff_full":{".class":"SymbolTableNode","kind":"Mdef","node":{".class":"Var","flags":["is_initialized_in_class","is_ready","has_explicit_value"],"fullname":"fluxflow.config.TrainingConfig.train_diff_full","name":"train_diff_full","setter_type":null,"type":"builtins.bool"}},"train_no_gan":{".class":"SymbolTableNode","kind":"Mdef","node":{".class":"Var","flags":["is_initialized_in_class","is_ready","has_explicit_value"],"fullname":"fluxflow.config.TrainingConfig.train_no_gan","name":"train_no_gan","setter_type":null,"type":"builtins.bool"}},"train_spade":{".class":"SymbolTableNode","kind":"Mdef","node":{".class":"Var","flags":["is_initialized_in_class","is_ready","has_explicit_value"],"fullname":"fluxflow.config.TrainingConfig.train_spade","name":"train_spade","setter_type":null,"type":"builtins.bool"}},"train_vae":{".class":"SymbolTableNode","kind":"Mdef","node":{".class":"Var","flags":["is_initialized_in_class","is_ready","has_explicit_value"],"fullname":"fluxflow.config.TrainingConfig.train_vae","name":"train_vae","setter_type":null,"type":"builtins.bool"}},"training_steps":{".class":"SymbolTableNode","kind":"Mdef","node":{".class":"Var","flags":["is_initialized_in_class","is_ready","has_explicit_value"],"fullname":"fluxflow.config.TrainingConfig.training_steps","name":"training_steps","setter_type":null,"type":"builtins.int"}},"use_fp16":{".class":"SymbolTableNode","kind":"Mdef","node":{".class":"Var","flags":["is_initialized_in_class","is_ready","has_explicit_value"],"fullname":"fluxflow.config.TrainingConfig.use_fp16","name":"use_fp16","setter_type":null,"type":"builtins.bool"}},"workers":{".class":"SymbolTableNode","kind":"Mdef","node":{".class":"Var","flags":["is_initialized_in_class","is_ready","has_explicit_value"],"fullname":"fluxflow.config.TrainingConfig.workers","name":"workers","setter_type":null,"type":"builtins.int"}}},"self_type":{".class":"TypeVarType","default":{".class":"AnyType","missing_import_name":null,"source_any":null,"type_of_any":4},"fullname":"fluxflow.config.TrainingConfig.Self","id":0,"name":"Self","namespace":"","upper_bound":"fluxflow.config.TrainingConfig","values":[],"variance":0},"slots":null,"tuple_type":null,"type_vars":[],"typeddict_type":null}},"__annotations__":{".class":"SymbolTableNode","kind":"Gdef","node":{".class":"Var","flags":["is_ready"],"fullname":"fluxflow.config.__annotations__","name":"__annotations__","setter_type":null,"type":{".class":"Instance","args":["builtins.str",{".class":"AnyType","missing_import_name":null,"source_any":null,"type_of_any":6}],"extra_attrs":null,"type_ref":"builtins.dict"}}},"__doc__":{".class":"SymbolTableNode","kind":"Gdef","node":{".class":"Var","flags":["is_ready"],"fullname":"fluxflow.config.__doc__","name":"__doc__","setter_type":null,"type":"builtins.str"}},"__file__":{".class":"SymbolTableNode","kind":"Gdef","node":{".class":"Var","flags":["is_ready"],"fullname":"fluxflow.config.__file__","name":"__file__","setter_type":null,"type":"builtins.str"}},"__name__":{".class":"SymbolTableNode","kind":"Gdef","node":{".class":"Var","flags":["is_ready"],"fullname":"fluxflow.config.__name__","name":"__name__","setter_type":null,"type":"builtins.str"}},"__package__":{".class":"SymbolTableNode","kind":"Gdef","node":{".class":"Var","flags":["is_ready"],"fullname":"fluxflow.config.__package__","name":"__package__","setter_type":null,"type":"builtins.str"}},"__spec__":{".class":"SymbolTableNode","kind":"Gdef","node":{".class":"Var","flags":["is_ready"],"fullname":"fluxflow.config.__spec__","name":"__spec__","setter_type":null,"type":"_frozen_importlib.ModuleSpec"}},"create_default_config":{".class":"SymbolTableNode","kind":"Gdef","node":{".class":"FuncDef","abstract_status":0,"arg_kinds":[1],"arg_names":["save_path"],"dataclass_transform_spec":null,"deprecated":null,"flags":[],"fullname":"fluxflow.config.create_default_config","name":"create_default_config","original_first_arg":"save_path","type":{".class":"CallableType","arg_kinds":[1],"arg_names":["save_path"],"arg_types":[{".class":"UnionType","items":["builtins.str","pathlib.Path",{".class":"NoneType"}],"uses_pep604_syntax":false}],"fallback":"builtins.function","from_concatenate":false,"implicit":false,"imprecise_arg_kinds":false,"is_bound":false,"is_ellipsis_args":false,"name":"create_default_config","ret_type":"fluxflow.config.FluxFlowConfig","type_guard":null,"type_is":null,"unpack_kwargs":false,"variables":[]}}},"field_validator":{".class":"SymbolTableNode","cross_ref":"pydantic.functional_validators.field_validator","kind":"Gdef"},"load_config":{".class":"SymbolTableNode","kind":"Gdef","node":{".class":"FuncDef","abstract_status":0,"arg_kinds":[0],"arg_names":["path"],"dataclass_transform_spec":null,"deprecated":null,"flags":[],"fullname":"fluxflow.config.load_config","name":"load_config","original_first_arg":"path","type":{".class":"CallableType","arg_kinds":[0],"arg_names":["path"],"arg_types":[{".class":"UnionType","items":["builtins.str","pathlib.Path"],"uses_pep604_syntax":true}],"fallback":"builtins.function","from_concatenate":false,"implicit":false,"imprecise_arg_kinds":false,"is_bound":false,"is_ellipsis_args":false,"name":"load_config","ret_type":"fluxflow.config.FluxFlowConfig","type_guard":null,"type_is":null,"unpack_kwargs":false,"variables":[]}}},"yaml":{".class":"SymbolTableNode","cross_ref":"yaml","kind":"Gdef"}},"path":"/opt/homebrew/anaconda3/lib/python3.10/site-packages/fluxflow/config.py"}